[
    {
        "key": "dbln",
        "value": "%7B%2261561611154753%22%3A%223VrBK1uq%22%2C%2261562014353269%22%3A%22COF45FJ4%22%2C%22100075793152380%22%3A%22VzAkQnSR%22%7D",
        "domain": "facebook.com",
        "path": "/login/device-based/",
        "hostOnly": false,
        "creation": "2024-08-28T04:13:52.706Z",
        "lastAccessed": "2024-08-28T04:13:52.713Z"
    },
    {
        "key": "datr",
        "value": "WoHHZkukX9aE9pSM4nc1_1bO",
        "domain": "facebook.com",
        "path": "/",
        "hostOnly": false,
        "creation": "2024-08-28T04:13:52.713Z",
        "lastAccessed": "2024-08-28T04:13:52.713Z"
    },
    {
        "key": "sb",
        "value": "WoHHZsScWb0iJ-9It3rkt1AU",
        "domain": "facebook.com",
        "path": "/",
        "hostOnly": false,
        "creation": "2024-08-28T04:13:52.713Z",
        "lastAccessed": "2024-08-28T04:13:52.713Z"
    },
    {
        "key": "locale",
        "value": "en_US",
        "domain": "facebook.com",
        "path": "/",
        "hostOnly": false,
        "creation": "2024-08-28T04:13:52.713Z",
        "lastAccessed": "2024-08-28T04:13:52.713Z"
    },
    {
        "key": "ps_l",
        "value": "1",
        "domain": "facebook.com",
        "path": "/",
        "hostOnly": false,
        "creation": "2024-08-28T04:13:52.713Z",
        "lastAccessed": "2024-08-28T04:13:52.713Z"
    },
    {
        "key": "ps_n",
        "value": "1",
        "domain": "facebook.com",
        "path": "/",
        "hostOnly": false,
        "creation": "2024-08-28T04:13:52.713Z",
        "lastAccessed": "2024-08-28T04:13:52.713Z"
    },
    {
        "key": "vpd",
        "value": "v1%3B688x360x2",
        "domain": "facebook.com",
        "path": "/",
        "hostOnly": false,
        "creation": "2024-08-28T04:13:52.713Z",
        "lastAccessed": "2024-08-28T04:13:52.713Z"
    },
    {
        "key": "m_pixel_ratio",
        "value": "2",
        "domain": "facebook.com",
        "path": "/",
        "hostOnly": false,
        "creation": "2024-08-28T04:13:52.713Z",
        "lastAccessed": "2024-08-28T04:13:52.713Z"
    },
    {
        "key": "wd",
        "value": "360x688",
        "domain": "facebook.com",
        "path": "/",
        "hostOnly": false,
        "creation": "2024-08-28T04:13:52.713Z",
        "lastAccessed": "2024-08-28T04:13:52.713Z"
    },
    {
        "key": "c_user",
        "value": "100075793152380",
        "domain": "facebook.com",
        "path": "/",
        "hostOnly": false,
        "creation": "2024-08-28T04:13:52.713Z",
        "lastAccessed": "2024-08-28T04:13:52.713Z"
    },
    {
        "key": "fr",
        "value": "0sZWtfE6yGWbwkVDr.AWUxGwT6Vc5pPKGXiwaKan5pBUg.Bmx4Fa..AAA.0.0.BmzqM3.AWWp0gQIAI0",
        "domain": "facebook.com",
        "path": "/",
        "hostOnly": false,
        "creation": "2024-08-28T04:13:52.713Z",
        "lastAccessed": "2024-08-28T04:13:52.713Z"
    },
    {
        "key": "xs",
        "value": "33%3ATpI_U4WL1fompA%3A2%3A1724818231%3A-1%3A5375",
        "domain": "facebook.com",
        "path": "/",
        "hostOnly": false,
        "creation": "2024-08-28T04:13:52.713Z",
        "lastAccessed": "2024-08-28T04:13:52.713Z"
    },
    {
        "key": "wl_cbv",
        "value": "v2%3Bclient_version%3A2604%3Btimestamp%3A1724818249",
        "domain": "facebook.com",
        "path": "/",
        "hostOnly": false,
        "creation": "2024-08-28T04:13:52.713Z",
        "lastAccessed": "2024-08-28T04:13:52.713Z"
    },
    {
        "key": "fbl_st",
        "value": "100723192%3BT%3A28746973",
        "domain": "facebook.com",
        "path": "/",
        "hostOnly": false,
        "creation": "2024-08-28T04:13:52.714Z",
        "lastAccessed": "2024-08-28T04:13:52.714Z"
    }
]
